uconf/__init__.py
uconf/action_parser.py
uconf/actions.py
uconf/cli.py
uconf/commands.py
uconf/config.py
uconf/constants.py
uconf/converter.py
uconf/fs.py
uconf/helpers.py
uconf/porcelain.py
uconf/rule_parser.py
uconf-0.4.1.data/scripts/uconf
uconf-0.4.1.dist-info/LICENSE
uconf-0.4.1.dist-info/METADATA
uconf-0.4.1.dist-info/WHEEL
uconf-0.4.1.dist-info/top_level.txt
uconf-0.4.1.dist-info/RECORD
