Metadata-Version: 2.1
Name: uconf
Version: 0.4.1
Summary: UConf, a smart tool for managing config files
Home-page: https://github.com/rbarrois/uconf/
Author: Raphaël Barrois
Author-email: raphael.barrois+uconf@polytechnique.org
License: BSD
Download-URL: https://pypi.python.org/pypi/uconf/
Keywords: configuration,management,uconf,confmgr,config
Platform: OS Independent
Classifier: Development Status :: 4 - Beta
Classifier: Environment :: Console
Classifier: Intended Audience :: System Administrators
Classifier: License :: OSI Approved :: BSD License
Classifier: Operating System :: OS Independent
Classifier: Programming Language :: Python
Classifier: Programming Language :: Python :: 3
Classifier: Programming Language :: Python :: 3.6
Classifier: Programming Language :: Python :: 3.7
Classifier: Programming Language :: Python :: 3.8
Classifier: Topic :: System :: Installation/Setup
Classifier: Topic :: System :: Systems Administration
Requires-Dist: fslib (>=0.3.4)
Requires-Dist: tdparser
Requires-Dist: confutils (>=0.3.6)
